openglass/__init__.py
openglass/settings.py
openglass/telegram.py
openglass/twitter.py
openglass/utility.py
openglass-0.3.0.dist-info/entry_points.txt
openglass-0.3.0.dist-info/LICENSE
openglass-0.3.0.dist-info/WHEEL
openglass-0.3.0.dist-info/METADATA
openglass-0.3.0.dist-info/RECORD
